{
    "info": {
        "name": "Volumio Selection",
        "albumart": "https://radio-directory.firebaseapp.com/volumio/src/images/volumio-selection.png"
    },
    "radios": [
        {
            "title": "Smooth Radio",
            "albumartUri": "https://cdn.onlineradiobox.com/img/l/4/964.v13.png",
            "uri": "https://media-ssl.musicradio.com/SmoothLondonMP3"
        },
        {
            "title": "Capital FM",
            "albumartUri": "https://cdn.onlineradiobox.com/img/l/8/1018.v21.png",
            "uri": "https://media-ssl.musicradio.com/Capital"
        },        
        {
            "title": "Heart FM",
            "albumartUri": "http://cdn.onlineradiobox.com/img/l/7/1047.v20.png",
            "uri": "https://media-ssl.musicradio.com/HeartUK"
        },        
        {
            "title": "LBC",
            "albumartUri": "http://cdn.onlineradiobox.com/img/l/4/994.v8.png",
            "uri": "https://media-ssl.musicradio.com/LBCLondon"
        },        
        {
            "title": "Dance UK Radio",
            "albumartUri": "http://cdn.onlineradiobox.com/img/l/7/43387.v9.png",
            "uri": "http://dancestream.danceradiouk.com/;"
        },              
        {
            "title": "Classic Rock Florida",
            "albumartUri": "http://cdn.onlineradiobox.com/img/l/2/26822.v8.png",
            "uri": "http://ais-edge105-live365-dal02.cdnstream.com/a06375"
        },                              
        {
            "title": "98.1 KISS*FM",
            "albumartUri": "https://encrypted-tbn0.gstatic.com/images?q=tbn:ANd9GcRK5dq366malnqK0YFXNmmtlIbLptf1Z5IeP0A6LLU&usqp=CAE&s",
            "uri": "http://a1.asurahosting.com:8840/radio.mp3"
        },        
        {
            "title": "BBC World Service",
	    "albumartUri": "https://ichef.bbci.co.uk/news/1024/cpsprodpb/F5F6/production/_96566926_bbc_wn_rgb.png",
            "uri": "http://stream.live.vc.bbcmedia.co.uk/bbc_world_service"
        },
        {
            "title": "ArtSound FM 92.7",   
            "uri": "http://119.15.96.188/stream2.mp3"
        },
        {
            "title": "Classic FM",
            "uri": "http://vis.media-ice.musicradio.com/ClassicFMMP3"
        },
        {
            "title": "CDNX 1 - Classic & New Indie Alt",
            "uri": "http://svr1.msmn.co:8136"
        },
        {
            "title": "CDNX 2 - New & Upfront Indie Alt",
            "uri": "http://msmn.co:8118"
        },
        {
            "title": "EuropaRadioJazz - 88.3 Smooth Jazz HD",
            "uri": "http://onair.europaradiojazz.org/radio/8000/sd"
        },
        {
            "title": "France Musique Classique Plus",
            "uri": "http://direct.francemusique.fr/live/francemusiqueclassiqueplus-hifi.mp3"
        },
        {
            "title": "France Musique La Contemporaine",
            "uri": "http://direct.francemusique.fr/live/francemusiquelacontemporaine-hifi.mp3"
        },
        {
            "title": "France Musique La Jazz",
            "uri": "http://direct.francemusique.fr/live/francemusiquelajazz-hifi.mp3"
        },
        {
            "title": "Ibiza Sonica",
            "uri": "http://95.211.3.65:8136/listen.pls?sid=1"
        },
        {
            "title": "KEXP 90.3 FM Seattle",
            "uri": "http://live-aacplus-64.kexp.org/kexp64.aac"
        },
        {
            "title": "Mix 106",
            "uri": "http://stream13.shoutcastsolutions.com/proxy/gbeaum00?mp=/stream"
        },
        {
            "title": "Naim Classical (FLAC)",
            "uri": "http://mscp3.live-streams.nl:8250/class-flac.flac"
        },
        {
            "title": "Naim Jazz (FLAC)",
            "uri": "http://mscp3.live-streams.nl:8340/jazz-flac.flac"
        },
        {
            "title": "Naim Radio (FLAC)",
            "uri": "http://mscp3.live-streams.nl:8360/flac.flac"
        },
        {
            "title": "NTS Live International",
            "uri": "http://stream-relay-geo.ntslive.net/stream2"
        },
        {
            "title": "Radio 24 Il Sole 24 Ore",
            "uri": "http://shoutcast.radio24.it:8000/"
        },
        {
            "title": "RadioJAZZ.FM",
            "uri": "https://radiojazz.out.airtime.pro/radiojazz_a"
        },
        {
            "title": "Radio Paradise",
            "uri": "http://stream-dc1.radioparadise.com/rp_192m.ogg"
        },
        {
            "title": "Radio Paradise (FLAC+)",
            "uri": "http://stream.radioparadise.com/flacm"
        },
        {
            "title": "Radio Paradise Mellow (FLAC+)",
            "uri": "http://stream.radioparadise.com/mellow-flacm"
        },
        {
            "title": "Radio Paradise Rock (FLAC+)",
            "uri": "http://stream.radioparadise.com/rock-flacm"
        },
        {
            "title": "Radio Paradise World (FLAC+)",
            "uri": "http://stream.radioparadise.com/world-etc-flacm"
        },
        {
            "title": "Radio Reload",
            "uri": "http://onair15.xdevel.com:7012/1"
        },
        {
            "title": "Radio Swiss Classic",
            "uri": "http://stream.srg-ssr.ch/m/rsc_de/aacp_96"
        },
        {
            "title": "Radio Swiss Jazz",
            "uri": "http://stream.srg-ssr.ch/m/rsj/aacp_96"
        },
        {
            "title": "Radio X London",
            "uri": "http://media-sov.musicradio.com:80/RadioXLondonMP3"
        },
        {
            "title": "San Diego Jazz 88.3",
            "uri": "http://listen.jazz88.org/ksds.mp3"
        },
        {
            "title": "FIP1",
            "uri": "http://direct.fipradio.fr/live/fip-midfi.mp3"
        },
        {
            "title": "FIP2",
            "uri": "http://icecast.radiofrance.fr/fip-midfi.mp3"
        },
        {
            "title": "FIP Rock",
            "uri": "http://direct.fipradio.fr/live/fip-webradio1.mp3"
        },
        {
            "title": "FIP Jazz",
            "uri": "http://direct.fipradio.fr/live/fip-webradio2.mp3"
        },
        {
            "title": "FIP Groove",
            "uri": "http://direct.fipradio.fr/live/fip-webradio3.mp3"
        },
        {
            "title": "FIP Monde",
            "uri": "http://direct.fipradio.fr/live/fip-webradio4.mp3"
        },
        {
            "title": "FIP Tout FIP",
            "uri": "http://direct.fipradio.fr/live/fip-webradio5.mp3"
        },
        {
            "title": "FIP Disquaire",
            "uri": "http://direct.fipradio.fr/live/fip-webradio6.mp3"
        },
        {
            "title": "Radio Perfecto",
            "uri": "http://radioperfecto.net-radio.fr/perfecto.mp3"
        },
        {
            "title": "France Culture",
            "uri": "http://direct.franceculture.fr/live/franceculture-midfi.mp3"
        },
        {
            "title": "France Inter",
            "uri": "http://direct.franceinter.fr/live/franceinter-midfi.mp3"
        },
        {
            "title": "France Musique",
            "uri": "http://direct.francemusique.fr/live/francemusique-midfi.mp3"
        },
        {
            "title": "France Info",
            "uri": "https://stream.radiofrance.fr/franceinfo/franceinfo_hifi.m3u8"
        },
        {
            "title": "SomaFM-GrooveSalad",
            "uri": "http://198.24.44.211/groovesalad-128-aac"
        },
        {
            "title": "BBC-Radio1",
            "uri": "https://raw.githubusercontent.com/mikepierce/internet-radio-streams/main/BBC-Radio1.m3u"
        },
        {
            "title": "BBC-Radio2",
            "uri": "https://raw.githubusercontent.com/mikepierce/internet-radio-streams/main/BBC-Radio2.m3u"
        },
        {
            "title": "BBC-Radio6",
            "uri": "https://raw.githubusercontent.com/mikepierce/internet-radio-streams/main/BBC-Radio6.m3u"
        },
        {
            "title": "BBC-WorldService",
            "uri": "https://raw.githubusercontent.com/mikepierce/internet-radio-streams/main/BBC-WorldService.m3u"
        },
        {
            "title": "RadioParadise-Global",
            "uri": "https://raw.githubusercontent.com/mikepierce/internet-radio-streams/main/RadioParadise-Global.m3u"
        },
        {
            "title": "RadioParadise-MainMix",
            "uri": "https://raw.githubusercontent.com/mikepierce/internet-radio-streams/main/RadioParadise-MainMix.m3u"
        },
        {
            "title": "NTS1",
            "uri": "https://raw.githubusercontent.com/mikepierce/internet-radio-streams/main/NTS1.m3u"
        },
        {
            "title": "NTS2",
            "uri": "https://raw.githubusercontent.com/mikepierce/internet-radio-streams/main/NTS2.m3u"
        },
        {
            "title": "Nectarine",
            "uri": "https://raw.githubusercontent.com/mikepierce/internet-radio-streams/main/Nectarine.m3u"
        },
        {
            "title": "Classic Vinyl HD",
            "uri": "https://testbench.walmradio.com/SAM-CLASSIC/web/generate_m3u_opus.php"
        },
        {
            "title": "101 Smooth Jazz",
            "uri": "http://www.101smoothjazz.com/101-smoothjazz.m3u"
        },
        {
            "title": "Super Radyo DZBB",
            "uri": "http://stream.gmanews.tv/ioslive/livestream/chunklist.m3u8?wowzasessionid=693701106"
        },
        {
            "title": "Dance Wave",
            "uri": "https://dancewave.online/dance.mp3"
        },
        {
            "title": "REYFM",
            "uri": "https://listen.reyfm.de/original_192kbps.mp3"
        },
        {
            "title": "Adroit Jazz Underground",
            "uri": "https://icecast.walmradio.com:8443/jazz"
        },
        {
            "title": "Walm Old Time",
            "uri": "https://icecast.walmradio.com:8443/otr"
        },
        {
            "title": "Deep House Lounge",
            "uri": "http://198.15.94.34:8006/stream"
        },
        {
            "title": "Jazz Radio Blues",
            "uri": "http://jazzblues.ice.infomaniak.ch/jazzblues-high.mp3"
        },
        {
            "title": "Linn Classic",
            "uri": "http://radio.linn.co.uk:8004/autodj"
        },
        {
            "title": "Linn Jazz",
            "uri": "http://radio.linn.co.uk:8000/autodj"
        },
        {
            "title": "Linn Radio",
            "uri": "http://radio.linn.co.uk:8003/autodj"
        },
        {
            "title": "RP ROCK",
            "uri": "http://stream.radioparadise.com/rock-flacm"
        },
        {
            "title": "NEW CLEAR RADIO",
            "uri": "http://live.ncradio.fm/320"
        },
        {
            "title": "NME 1",
            "uri": "http://listen-nme.sharp-stream.com/nme1high.mp3"
        },
        {
            "title": "NME 2",
            "uri": "http://listen-nme.sharp-stream.com/nme2high.mp3"
        },
        {
            "title": "San Francisco 70s",
            "uri": "https://a1.asurahosting.com:10990/radio.mp3"
        },
        {
            "title": "timewarp ireland",
            "uri": "http://141.94.205.245:8052/stream"
        },
        {
            "title": "JB Radio2",
            "uri": "https://maggie.torontocast.com:8076/flac"
        },
        {
            "title": "Naim Radio Flac",
            "uri": "http://mscp3.live-streams.nl:8360/flac.flac"
        },
        {
            "title": "Superstereo 1",
            "uri": "http://icecast.centaury.cl:7570/SuperStereoHiRes1"
        },
        {
            "title": "Suoerstereo 2",
            "uri": "http://icecast.centaury.cl:7570/SuperStereoHiRes2"
        },
        {
            "title": "Superstereo 3",
            "uri": "http://icecast.centaury.cl:7570/SuperStereoHiRes3"
        },
        {
            "title": "Superstereo 4",
            "uri": "http://icecast.centaury.cl:7570/SuperStereoHiRes4"
        },
        {
            "title": "SuperStereo 5",
            "uri": "http://icecast.centaury.cl:7570/SuperStereoHiRes5"
        },
        {
            "title": "SuperStereo 6",
            "uri": "http://icecast.centaury.cl:7570/SuperStereoHiRes6"
        },
        {
            "title": "SuperStereo 7",
            "uri": "http://icecast.centaury.cl:7560/SuperStereoNoData7"
        }
    ]
}

